foundrybot/__init__.py
foundrybot/error.py
foundrybot/foundrybot_client.py
foundrybot/resource.py
foundrybot/version.py
foundrybot-1.0.dist-info/DESCRIPTION.rst
foundrybot-1.0.dist-info/METADATA
foundrybot-1.0.dist-info/RECORD
foundrybot-1.0.dist-info/WHEEL
foundrybot-1.0.dist-info/metadata.json
foundrybot-1.0.dist-info/top_level.txt
