Metadata-Version: 2.0
Name: foundrybot
Version: 1.0
Summary: Foundrybot python bindings
Home-page: https://github.com/FoundryAI/foundrybot-python
Author: Nick Gerner
Author-email: nick@foundry.ai
License: UNKNOWN
Download-URL: https://github.com/FoundryAI/foundrybot-python/archive/1.0.tar.gz
Keywords: foundrybot,foundry.ai,foundrydc
Platform: UNKNOWN
Requires-Dist: pydash
Requires-Dist: requests
